__init__.py
soundingcenter/SoundingCenter.py
soundingcenter/__init__.py
soundingcenter/test_api.py
soundingcenter-1.2.1.dist-info/LICENSE
soundingcenter-1.2.1.dist-info/METADATA
soundingcenter-1.2.1.dist-info/WHEEL
soundingcenter-1.2.1.dist-info/top_level.txt
soundingcenter-1.2.1.dist-info/RECORD
