Metadata-Version: 2.1
Name: soundingcenter
Version: 1.2.1
Summary: A python lib to use the sounding center api
Author-email: Niklas Wildenburg <niklas.wildenburg@graw.de>
License: MIT License
Project-URL: Homepage, https://github.com/GrawRadiosondes/sounding-center-python-api
Project-URL: Bug Tracker, https://github.com/GrawRadiosondes/sounding-center-python-api/issues
Classifier: Programming Language :: Python :: 3
Classifier: License :: OSI Approved :: MIT License
Classifier: Operating System :: OS Independent
Requires-Python: >=3.10
License-File: LICENSE
Requires-Dist: requests >=2.32.3
Provides-Extra: dev
Requires-Dist: Faker >=28.1.0 ; extra == 'dev'
Requires-Dist: python-dotenv ~=1.0.1 ; extra == 'dev'
